ref/__init__.py
ref/cli.py
ref/config.py
ref/console.py
ref/diff_utils.py
ref/backends/__init__.py
ref/backends/zotero_client.py
ref/commands/__init__.py
ref/commands/_registry.py
ref/commands/listing.py
ref/commands/management.py
ref/commands/preview_client.py
ref/commands/preview_daemon.py
ref/commands/editing/__init__.py
ref/commands/editing/core.py
ref/commands/editing/labels.py
ref/commands/editing/relations.py
ref/picker/__init__.py
ref/picker/bindings.py
ref/picker/fzf.py
ref/picker/selectors.py
ref/picker/session.py
ref/utils/__init__.py
ref/utils/collections.py
ref/utils/diffing.py
ref/utils/display.py
ref/utils/editor.py
ref/utils/items.py
ref/utils/query.py
ref/utils/search.py
ref/utils/system.py
ref/utils/zotero.py
Refero-0.1.0.dist-info/METADATA
Refero-0.1.0.dist-info/WHEEL
Refero-0.1.0.dist-info/entry_points.txt
Refero-0.1.0.dist-info/top_level.txt
Refero-0.1.0.dist-info/RECORD
