Metadata-Version: 2.1
Name: Refero
Version: 0.1.0
Summary: A TUI/CLI reference manager based on Zotero, built with pyzotero and featuring an fzf-based selector.
Author-email: Shibing Chu <chu.shibing@gmail.com>
License: MIT License
Project-URL: Homepage, https://github.com/chu-/Refero/
Project-URL: Repository, https://github.com/chu-/Refero/
Requires-Python: >=3.9
Requires-Dist: typer>=0.9
Requires-Dist: PyYAML>=6.0
Requires-Dist: rich>=13.0.0
Requires-Dist: pyzotero>=1.5
Requires-Dist: socksio>=1.0.0
Requires-Dist: requests>=2.31.0
Requires-Dist: feedparser>=6.0.0
Requires-Dist: markdown>=3.5
Requires-Dist: markdownify>=0.11
Requires-Dist: fast-diff-match-patch>=2.0.0
